imgwrench/__init__.py
imgwrench/__main__.py
imgwrench/cli.py
imgwrench/info.py
imgwrench/param.py
imgwrench/commands/__init__.py
imgwrench/commands/blackwhite.py
imgwrench/commands/collage.py
imgwrench/commands/colorfix.py
imgwrench/commands/crop.py
imgwrench/commands/dither.py
imgwrench/commands/filmstrip.py
imgwrench/commands/flip.py
imgwrench/commands/frame.py
imgwrench/commands/framecrop.py
imgwrench/commands/grid.py
imgwrench/commands/quad.py
imgwrench/commands/resize.py
imgwrench/commands/save.py
imgwrench/commands/stack.py
tests/__init__.py
tests/images.py
tests/test_blackwhite.py
tests/test_collage.py
tests/test_colorfix.py
tests/test_crop.py
tests/test_dither.py
tests/test_filmstrip.py
tests/test_flip.py
tests/test_frame.py
tests/test_framecrop.py
tests/test_imgwrench.py
tests/test_param.py
tests/test_quad.py
tests/test_resize.py
tests/test_save.py
tests/test_stack.py
tests/utils.py
tests/images/red-blue.png
tests/images/town.jpg
imgwrench-0.17.0.dist-info/AUTHORS.rst
imgwrench-0.17.0.dist-info/LICENSE
imgwrench-0.17.0.dist-info/METADATA
imgwrench-0.17.0.dist-info/WHEEL
imgwrench-0.17.0.dist-info/entry_points.txt
imgwrench-0.17.0.dist-info/top_level.txt
imgwrench-0.17.0.dist-info/RECORD
