Metadata-Version: 2.1
Name: imgwrench
Version: 0.17.0
Summary: A highly opinionated image processor for the commandline.
Home-page: https://github.com/luphord/imgwrench
Author: luphord
Author-email: luphord@protonmail.com
License: MIT license
Keywords: imgwrench
Classifier: Development Status :: 3 - Alpha
Classifier: Intended Audience :: Developers
Classifier: License :: OSI Approved :: MIT License
Classifier: Natural Language :: English
Classifier: Programming Language :: Python :: 3
Classifier: Programming Language :: Python :: 3.8
Classifier: Programming Language :: Python :: 3.9
Classifier: Programming Language :: Python :: 3.10
License-File: LICENSE
License-File: AUTHORS.rst
Requires-Dist: Click (<8.1,>=6.0)
Requires-Dist: Pillow (<9,>=5.0)
Requires-Dist: numpy (>=1.10)
